stevent_manager/__init__.py
stevent_manager/__main__.py
stevent_manager/app.py
stevent_manager/db.py
stevent_manager/models.py
stevent_manager-0.1.5.dist-info/METADATA
stevent_manager-0.1.5.dist-info/WHEEL
stevent_manager-0.1.5.dist-info/entry_points.txt
stevent_manager-0.1.5.dist-info/RECORD
