Metadata-Version: 2.1
Name: stevent-manager
Version: 0.1.5
Summary: 
Author: stevepurpose
Author-email: stevenpurpose@gmail.com
Requires-Python: >=3.8,<4.0
Classifier: Programming Language :: Python :: 3
Classifier: Programming Language :: Python :: 3.8
Classifier: Programming Language :: Python :: 3.9
Classifier: Programming Language :: Python :: 3.10
Classifier: Programming Language :: Python :: 3.11
Classifier: Programming Language :: Python :: 3.12
Classifier: Programming Language :: Python :: 3.13
Requires-Dist: bcrypt (>=4.2.1,<5.0.0)
Requires-Dist: passlib (>=1.7.4,<2.0.0)
Requires-Dist: pydantic (>=2.10.2,<3.0.0)
Requires-Dist: pyjwt (<2.10)
Requires-Dist: pymongo (==3.12.0)
Requires-Dist: python-dotenv (>=1.0.1,<2.0.0)
Requires-Dist: typer (>=0.14.0,<0.15.0)
